clonedp/__init__.py
clonedp/__init__.pyi
clonedp/common.py
clonedp/errors.py
clonedp/items.py
clonedp/version.py
clonedp/_base/base.py
clonedp/_base/base.pyi
clonedp/_base/chromium.py
clonedp/_base/chromium.pyi
clonedp/_base/driver.py
clonedp/_base/driver.pyi
clonedp/_configs/chromium_options.py
clonedp/_configs/chromium_options.pyi
clonedp/_configs/options_manage.py
clonedp/_configs/options_manage.pyi
clonedp/_configs/session_options.py
clonedp/_configs/session_options.pyi
clonedp/_elements/chromium_element.py
clonedp/_elements/chromium_element.pyi
clonedp/_elements/none_element.py
clonedp/_elements/none_element.pyi
clonedp/_elements/session_element.py
clonedp/_elements/session_element.pyi
clonedp/_functions/browser.py
clonedp/_functions/browser.pyi
clonedp/_functions/by.py
clonedp/_functions/cli.py
clonedp/_functions/cookies.py
clonedp/_functions/cookies.pyi
clonedp/_functions/elements.py
clonedp/_functions/elements.pyi
clonedp/_functions/keys.py
clonedp/_functions/keys.pyi
clonedp/_functions/locator.py
clonedp/_functions/locator.pyi
clonedp/_functions/settings.py
clonedp/_functions/settings.pyi
clonedp/_functions/texts.py
clonedp/_functions/tools.py
clonedp/_functions/tools.pyi
clonedp/_functions/web.py
clonedp/_functions/web.pyi
clonedp/_pages/chromium_base.py
clonedp/_pages/chromium_base.pyi
clonedp/_pages/chromium_frame.py
clonedp/_pages/chromium_frame.pyi
clonedp/_pages/chromium_page.py
clonedp/_pages/chromium_page.pyi
clonedp/_pages/chromium_tab.py
clonedp/_pages/chromium_tab.pyi
clonedp/_pages/mix_tab.py
clonedp/_pages/mix_tab.pyi
clonedp/_pages/session_page.py
clonedp/_pages/session_page.pyi
clonedp/_pages/web_page.py
clonedp/_pages/web_page.pyi
clonedp/_units/actions.py
clonedp/_units/actions.pyi
clonedp/_units/clicker.py
clonedp/_units/clicker.pyi
clonedp/_units/console.py
clonedp/_units/console.pyi
clonedp/_units/cookies_setter.py
clonedp/_units/cookies_setter.pyi
clonedp/_units/downloader.py
clonedp/_units/downloader.pyi
clonedp/_units/listener.py
clonedp-1.0.1.dist-info/METADATA
clonedp-1.0.1.dist-info/WHEEL
clonedp-1.0.1.dist-info/top_level.txt
clonedp-1.0.1.dist-info/RECORD
