Metadata-Version: 2.4
Name: clonedp
Version: 1.0.1
Summary: xxx
Author-email: xxx <xxx@example.com>
License: MIT
Project-URL: Homepage, https://example.com
Classifier: Programming Language :: Python :: 3
Classifier: License :: OSI Approved :: MIT License
Classifier: Operating System :: OS Independent
Requires-Python: >=3.6
